{
  "title": "Nineteen Eighty-Four",
  "scenesAnalyzed": 72,
  "totalBeats": 1023,
  "avgBeatsPerKWord": 13.3,
  "beatDistribution": {
    "breathe": 0.163,
    "inform": 0.212,
    "advance": 0.223,
    "bond": 0.053,
    "turn": 0.058,
    "reveal": 0.109,
    "shift": 0.022,
    "expand": 0.077,
    "foreshadow": 0.037,
    "resolve": 0.045
  },
  "mechanismDistribution": {
    "dialogue": 0.238,
    "thought": 0.212,
    "action": 0.21,
    "environment": 0.146,
    "narration": 0.155,
    "memory": 0.019,
    "document": 0.02,
    "comic": 0.001
  },
  "markovTransitions": {
    "breathe": {
      "breathe": 0.099,
      "advance": 0.241,
      "reveal": 0.074,
      "inform": 0.407,
      "resolve": 0.012,
      "expand": 0.037,
      "turn": 0.049,
      "foreshadow": 0.025,
      "bond": 0.049,
      "shift": 0.006
    },
    "inform": {
      "breathe": 0.094,
      "reveal": 0.178,
      "expand": 0.127,
      "advance": 0.333,
      "turn": 0.028,
      "inform": 0.085,
      "shift": 0.033,
      "bond": 0.042,
      "foreshadow": 0.052,
      "resolve": 0.028
    },
    "advance": {
      "inform": 0.199,
      "turn": 0.125,
      "reveal": 0.134,
      "bond": 0.056,
      "advance": 0.176,
      "expand": 0.069,
      "breathe": 0.111,
      "resolve": 0.065,
      "shift": 0.028,
      "foreshadow": 0.037
    },
    "bond": {
      "resolve": 0.137,
      "inform": 0.216,
      "expand": 0.118,
      "advance": 0.137,
      "breathe": 0.098,
      "reveal": 0.137,
      "bond": 0.059,
      "turn": 0.059,
      "shift": 0.039
    },
    "turn": {
      "advance": 0.327,
      "breathe": 0.073,
      "inform": 0.145,
      "resolve": 0.073,
      "reveal": 0.164,
      "bond": 0.091,
      "expand": 0.055,
      "shift": 0.036,
      "foreshadow": 0.036
    },
    "reveal": {
      "breathe": 0.069,
      "expand": 0.069,
      "inform": 0.265,
      "advance": 0.255,
      "turn": 0.069,
      "bond": 0.108,
      "resolve": 0.078,
      "shift": 0.029,
      "foreshadow": 0.029,
      "reveal": 0.029
    },
    "shift": {
      "advance": 0.4,
      "expand": 0.1,
      "breathe": 0.05,
      "turn": 0.1,
      "bond": 0.05,
      "inform": 0.25,
      "reveal": 0.05
    },
    "expand": {
      "foreshadow": 0.117,
      "expand": 0.104,
      "advance": 0.13,
      "reveal": 0.117,
      "inform": 0.351,
      "breathe": 0.104,
      "bond": 0.039,
      "resolve": 0.039
    },
    "foreshadow": {
      "expand": 0.091,
      "inform": 0.121,
      "breathe": 0.121,
      "advance": 0.242,
      "turn": 0.182,
      "reveal": 0.091,
      "shift": 0.03,
      "bond": 0.061,
      "resolve": 0.061
    },
    "resolve": {
      "breathe": 0.5,
      "shift": 0.045,
      "advance": 0.091,
      "expand": 0.091,
      "inform": 0.182,
      "reveal": 0.045,
      "foreshadow": 0.045
    }
  },
  "sampleAnchors": [
    "It was a bright cold day in April, and the clocks were striking thirteen.",
    "BIG BROTHER IS WATCHING YOU, the caption beneath it ran.",
    "The instrument (the telescreen, it was called) could be dimmed, but there was no way of shutting it off completely.",
    "You had to live--did live, from habit that became instinct--in the assumption that every sound you made was overheard, and, except in darkness, every movement scrutinized.",
    "The Ministry of Love was the really frightening one.",
    "The stuff was like nitric acid",
    "a peculiarly beautiful book",
    "if detected it was reasonably certain that it would be punished by death",
    "To mark the paper was the decisive act.",
    "The telescreen had changed over to strident military music."
  ],
  "id": "nineteen_eighty_four",
  "builtIn": true
}